builder/Group.py
builder/GroupList.py
builder/MatrixBook.py
builder/MatrixBuilder.py
builder/MyDialog.py
builder/MyMatrix.py
builder/Untitled.ico
builder/__init__.py
builder/__main__.py
builder/logo.ico
builder/mainLoader.py
builder/utils.py
builder/Saved_Matrix/dup.txt
builder/Saved_Matrix/example.txt
builder/Saved_Matrix/first.txt
builder/Saved_Matrix/temp.txt
builder/Saved_Matrix/whatisthis.txt
builder/output/haha.py
builder/output/output_example.py
sparse_matrix_builder-0.0.6.dist-info/LICENCE.txt
sparse_matrix_builder-0.0.6.dist-info/METADATA
sparse_matrix_builder-0.0.6.dist-info/WHEEL
sparse_matrix_builder-0.0.6.dist-info/entry_points.txt
sparse_matrix_builder-0.0.6.dist-info/top_level.txt
sparse_matrix_builder-0.0.6.dist-info/RECORD
